{"stats":{"minecraft:mined":{"minecraft:redstone_block":1,"minecraft:white_bed":1,"minecraft:comparator":2,"minecraft:brewing_stand":1,"minecraft:oak_fence":1,"minecraft:poppy":1,"minecraft:redstone_wire":8,"minecraft:campfire":2,"minecraft:tall_grass":1,"minecraft:cartography_table":1,"minecraft:hay_block":7,"minecraft:spruce_stairs":5,"minecraft:iron_ore":1,"minecraft:fletching_table":1,"minecraft:yellow_bed":1,"minecraft:grass":2,"minecraft:bookshelf":44,"regions_unexplored:oak_shrub":1,"minecraft:zombie_head":1,"regions_unexplored:medium_grass":1,"minecraft:stone":25},"minecraft:used":{"minecraft:stone_pickaxe":47,"minecraft:ender_pearl":1,"minecraft:iron_sword":41,"minecraft:cooked_chicken":1,"minecraft:firework_rocket":1,"minecraft:bread":7,"minecraft:map":1,"minecraft:cobblestone":4,"minecraft:pumpkin_pie":2},"minecraft:killed":{"minecraft:iron_golem":1,"minecraft:horse":1,"minecraft:cow":2},"minecraft:custom":{"minecraft:interact_with_smithing_table":1,"lootr:looted_stat":6,"minecraft:interact_with_furnace":7,"minecraft:mob_kills":5,"minecraft:interact_with_crafting_table":2,"minecraft:eat_cake_slice":4,"minecraft:time_since_death":15602,"minecraft:sleep_in_bed":1,"minecraft:climb_one_cm":584,"minecraft:time_since_rest":15629,"minecraft:sprint_one_cm":105827,"minecraft:damage_taken":1327,"minecraft:walk_one_cm":73958,"minecraft:drop":11,"minecraft:damage_dealt":1691,"minecraft:fly_one_cm":20987,"minecraft:crouch_one_cm":247,"minecraft:play_time":30276,"minecraft:deaths":1,"minecraft:sneak_time":189,"minecraft:jump":164,"minecraft:walk_on_water_one_cm":205,"minecraft:total_world_time":30276,"minecraft:interact_with_smoker":1,"minecraft:fall_one_cm":2380},"minecraft:crafted":{"minecraft:redstone":9,"minecraft:bread":21,"minecraft:wheat":63},"minecraft:picked_up":{"minecraft:charcoal":4,"minecraft:cooked_beef":1,"minecraft:redstone_block":1,"minecraft:leather":2,"minecraft:wooden_pickaxe":1,"minecraft:enchanted_book":1,"minecraft:brewing_stand":1,"minecraft:yellow_bed":1,"minecraft:paper":1,"minecraft:lantern":7,"minecraft:bone":2,"minecraft:item_frame":10,"minecraft:zombie_head":1,"minecraft:experience_bottle":1,"minecraft:apple":1,"minecraft:cartography_table":1,"minecraft:wheat_seeds":1,"minecraft:comparator":2,"minecraft:iron_ingot":6,"minecraft:beef":4,"minecraft:stone_pickaxe":2,"minecraft:cooked_chicken":1,"minecraft:oak_boat":2,"minecraft:poppy":2,"minecraft:rabbit":5,"minecraft:iron_sword":1,"minecraft:book":129,"minecraft:raw_iron":1,"minecraft:spruce_stairs":3,"regions_unexplored:oak_shrub":1,"minecraft:cookie":2,"minecraft:white_bed":1,"minecraft:redstone":8,"born_in_chaos_v1:damned_demomans_hat_helmet":1,"minecraft:firework_rocket":1,"minecraft:pumpkin_pie":2,"minecraft:hay_block":7,"minecraft:gold_ingot":2,"minecraft:emerald":2,"minecraft:mutton":2,"minecraft:cobblestone":25,"minecraft:ender_pearl":1},"minecraft:dropped":{"minecraft:wheat_seeds":1,"minecraft:cookie":2,"minecraft:lantern":1,"minecraft:spruce_stairs":3,"minecraft:filled_map":1,"minecraft:poppy":2,"minecraft:torch":1,"minecraft:oak_boat":2,"minecraft:wooden_pickaxe":1,"minecraft:paper":1}},"DataVersion":3465}